plantsai/__init__.py
plantsai/plantsai.py
PlantsAI-0.0.3.dist-info/LICENSE.md
PlantsAI-0.0.3.dist-info/METADATA
PlantsAI-0.0.3.dist-info/WHEEL
PlantsAI-0.0.3.dist-info/entry_points.txt
PlantsAI-0.0.3.dist-info/top_level.txt
PlantsAI-0.0.3.dist-info/RECORD
