Metadata-Version: 2.1
Name: PlantsAI
Version: 0.0.3
Summary: A powerful plant identifier to identify flowers, leaves, trees, and more in seconds! 🌱
Home-page: https://github.com/PlantsAI/plantsai
Author: Sajjad Aemmi
Author-email: sajjadaemmi@gmail.com
License-File: LICENSE.md
Requires-Dist: numpy
